sinkove/__init__.py
sinkove/client.py
sinkove/connector/__init__.py
sinkove/connector/connector.py
sinkove/datasets/__init__.py
sinkove/datasets/client.py
sinkove/datasets/metadata.py
sinkove/organizations/__init__.py
sinkove/organizations/client.py
sinkove_sdk-0.1.2.dist-info/METADATA
sinkove_sdk-0.1.2.dist-info/WHEEL
sinkove_sdk-0.1.2.dist-info/top_level.txt
sinkove_sdk-0.1.2.dist-info/RECORD
