Metadata-Version: 2.4
Name: sinkove-sdk
Version: 0.1.2
Summary: A Python SDK for interacting with Sinkove's AI dataset generation API.
Author-email: Sinkove Engineering Team <eng@sinkove.com>
Project-URL: homepage, https://cloud.sinkove.com
Requires-Python: >=3.12
Requires-Dist: requests>=2.31.0
Provides-Extra: dev
Requires-Dist: black>=23.9.1; extra == "dev"
Requires-Dist: ruff>=0.1.1; extra == "dev"
Requires-Dist: pytest>=7.2.0; extra == "dev"
Provides-Extra: packaging
Requires-Dist: build>=0.10.0; extra == "packaging"
Requires-Dist: twine>=4.0.2; extra == "packaging"
